Metadata-Version: 1.1
Name: fuo-bilibili
Version: 0.1.3
Summary: feeluown bilibili plugin
Home-page: https://github.com/feeluown/feeluown-bilibili
Author: cosven
Author-email: yinshaowen241@gmail.com
License: UNKNOWN
Keywords: feeluown,plugin,bilibili
Platform: UNKNOWN
Classifier: Development Status :: 3 - Alpha
Classifier: Programming Language :: Python :: 3.6
Classifier: Programming Language :: Python :: 3.7
Classifier: Programming Language :: Python :: 3.8
Classifier: Programming Language :: Python :: 3.9
Classifier: Programming Language :: Python :: 3 :: Only
